django_fluent_faq-1.0.dist-info/DESCRIPTION.rst
django_fluent_faq-1.0.dist-info/METADATA
django_fluent_faq-1.0.dist-info/RECORD
django_fluent_faq-1.0.dist-info/WHEEL
django_fluent_faq-1.0.dist-info/metadata.json
django_fluent_faq-1.0.dist-info/top_level.txt
fluent_faq/__init__.py
fluent_faq/appsettings.py
fluent_faq/managers.py
fluent_faq/models.py
fluent_faq/sitemaps.py
fluent_faq/urlresolvers.py
fluent_faq/urls.py
fluent_faq/views.py
fluent_faq/admin/__init__.py
fluent_faq/admin/base.py
fluent_faq/admin/faqcategoryadmin.py
fluent_faq/admin/faqquestionadmin.py
fluent_faq/locale/nl/LC_MESSAGES/django.mo
fluent_faq/locale/nl/LC_MESSAGES/django.po
fluent_faq/migrations/0001_initial.py
fluent_faq/migrations/__init__.py
fluent_faq/pagetypes/__init__.py
fluent_faq/pagetypes/faqpage/__init__.py
fluent_faq/pagetypes/faqpage/models.py
fluent_faq/pagetypes/faqpage/page_type_plugins.py
fluent_faq/pagetypes/faqpage/migrations/0001_initial.py
fluent_faq/pagetypes/faqpage/migrations/__init__.py
fluent_faq/pagetypes/faqpage/south_migrations/0001_initial.py
fluent_faq/pagetypes/faqpage/south_migrations/0002_add_seo_fields.py
fluent_faq/pagetypes/faqpage/south_migrations/0003_move_seo_fields.py
fluent_faq/pagetypes/faqpage/south_migrations/0004_remove_untranslated_fields.py
fluent_faq/pagetypes/faqpage/south_migrations/__init__.py
fluent_faq/pagetypes/faqpage/templates/admin/faqpage/change_form.html
fluent_faq/south_migrations/0001_initial.py
fluent_faq/south_migrations/__init__.py
fluent_faq/static/fluent_faq/admin/admin.css
fluent_faq/static/fluent_faq/img/admin/blank.gif
fluent_faq/static/fluent_faq/img/admin/world.gif
fluent_faq/templates/admin/fluent_faq/faqquestion/change_form.html
fluent_faq/templates/fluent_faq/base.html
fluent_faq/templates/fluent_faq/base_detail.html
fluent_faq/templates/fluent_faq/base_internal.html
fluent_faq/templates/fluent_faq/faqcategory_detail.html
fluent_faq/templates/fluent_faq/faqquestion_detail.html
fluent_faq/templates/fluent_faq/faqquestion_list.html
fluent_faq/templates/fluent_faq/index.html
fluent_faq/templates/fluent_faq/partials/similar_questions.html
fluent_faq/templatetags/__init__.py
fluent_faq/templatetags/fluent_faq_admin_tags.py
