Metadata-Version: 2.0
Name: django-fluent-faq
Version: 1.0
Summary: A FAQ engine for Django Fluent CMS
Home-page: https://github.com/edoburu/django-fluent-faq
Author: Diederik van der Boor
Author-email: opensource@edoburu.nl
License: Apache 2.0
Download-URL: https://github.com/edoburu/django-fluent-faq/zipball/master
Platform: UNKNOWN
Classifier: Development Status :: 4 - Beta
Classifier: Environment :: Web Environment
Classifier: Framework :: Django
Classifier: Intended Audience :: Developers
Classifier: License :: OSI Approved :: Apache Software License
Classifier: Operating System :: OS Independent
Classifier: Programming Language :: Python
Classifier: Programming Language :: Python :: 2.6
Classifier: Programming Language :: Python :: 2.7
Classifier: Programming Language :: Python :: 3
Classifier: Programming Language :: Python :: 3.3
Classifier: Programming Language :: Python :: 3.4
Classifier: Framework :: Django
Classifier: Framework :: Django :: 1.5
Classifier: Framework :: Django :: 1.6
Classifier: Framework :: Django :: 1.7
Classifier: Framework :: Django :: 1.8
Classifier: Framework :: Django :: 1.9
Classifier: Framework :: Django :: 1.10
Classifier: Topic :: Internet :: WWW/HTTP
Classifier: Topic :: Internet :: WWW/HTTP :: Dynamic Content
Classifier: Topic :: Software Development :: Libraries :: Python Modules
Requires: Django (>=1.5)
Requires-Dist: django-fluent-contents (>=1.0)
Requires-Dist: django-fluent-utils (>=1.0)
Requires-Dist: django-parler (>=1.0)
Requires-Dist: django-tag-parser (>=1.1)
Provides-Extra: faqpage
Requires-Dist: django-fluent-pages (>=0.9); extra == 'faqpage'
Provides-Extra: taggit
Requires-Dist: taggit; extra == 'taggit'
Requires-Dist: taggit-autosuggest; extra == 'taggit'
